ovos_PHAL/__init__.py
ovos_PHAL/__main__.py
ovos_PHAL/admin.py
ovos_PHAL/detection.py
ovos_PHAL/service.py
ovos_PHAL/version.py
ovos_phal-0.2.11.dist-info/licenses/LICENSE
ovos_phal-0.2.11.dist-info/METADATA
ovos_phal-0.2.11.dist-info/WHEEL
ovos_phal-0.2.11.dist-info/entry_points.txt
ovos_phal-0.2.11.dist-info/top_level.txt
ovos_phal-0.2.11.dist-info/RECORD
